.gitignore
README.rst
setup.py
e4u/__init__.py
e4u/code.py
e4u/loader.py
e4u/symbol.py
e4u/thumbnails.py
e4u/utils.py
e4u.egg-info/PKG-INFO
e4u.egg-info/SOURCES.txt
e4u.egg-info/dependency_links.txt
e4u.egg-info/requires.txt
e4u.egg-info/top_level.txt
e4u.egg-info/zip-safe
e4u/data/emoji4unicode.xml
test/__init__.py
test/test.py
utils/.gitignore
utils/__init__.py
utils/emoji_utils.py