Metadata-Version: 1.0
Name: e4u
Version: 0.2rc1
Summary: Python's emoji conversion (unicode emoji <=> carrier's emoji) library (emoji4unicode project wrapper library)
Home-page: https://github.com/lambdalisue/e4u
Author: Alisue
Author-email: lambdalisue@hashnote.net
License: BSD
Download-URL: https://github.com/lambdalisue/e4u/tarball/master
Keywords: emoji emoji4unicode mobile
Platform: UNKNOWN
Classifier: Intended Audience :: Developers
Classifier: License :: OSI Approved :: BSD License
Classifier: Programming Language :: Python
Classifier: Topic :: Internet :: WWW/HTTP
